pigweed-0.0.24.dist-info/licenses/LICENSE
pigweed_format/__init__.py
pigweed_format/__main__.py
pigweed_format/py.typed
pw_allocator/__init__.py
pw_allocator/__main__.py
pw_allocator/benchmarks.py
pw_allocator/heap_viewer.py
pw_allocator/py.typed
pw_arduino_build/__init__.py
pw_arduino_build/__main__.py
pw_arduino_build/builder.py
pw_arduino_build/core_installer.py
pw_arduino_build/file_operations.py
pw_arduino_build/log.py
pw_arduino_build/py.typed
pw_arduino_build/teensy_detector.py
pw_arduino_build/unit_test_client.py
pw_arduino_build/unit_test_runner.py
pw_arduino_build/unit_test_server.py
pw_arduino_build/core_patches/__init__.py
pw_arduino_build/core_patches/teensy/01-teensyduino_1.58.1-cpp17.diff
pw_arduino_build/core_patches/teensy/__init__.py
pw_bloat/__init__.py
pw_bloat/__main__.py
pw_bloat/binary_size_aggregator.py
pw_bloat/bloat.py
pw_bloat/bloaty_config.py
pw_bloat/build.py
pw_bloat/label.py
pw_bloat/label_output.py
pw_bloat/no_bloaty.py
pw_bloat/no_toolchains.py
pw_bloat/py.typed
pw_build/__init__.py
pw_build/bazel_query.py
pw_build/bazel_to_gn.py
pw_build/build_recipe.py
pw_build/collect_wheels.py
pw_build/copy_and_patch.py
pw_build/copy_from_cipd.py
pw_build/create_gn_venv.py
pw_build/create_python_tree.py
pw_build/error.py
pw_build/exec.py
pw_build/file_prefix_map.py
pw_build/generate_cc_blob_library.py
pw_build/generate_modules_lists.py
pw_build/generate_python_package.py
pw_build/generate_python_package_gn.py
pw_build/generate_python_requirements.py
pw_build/generate_python_wheel.py
pw_build/generate_python_wheel_cache.py
pw_build/generate_report.py
pw_build/generated_tests.py
pw_build/gn_resolver.py
pw_build/gn_target.py
pw_build/gn_writer.py
pw_build/host_tool.py
pw_build/merge_profraws.py
pw_build/mirror_tree.py
pw_build/nop.py
pw_build/pigweed_upstream_build.py
pw_build/pip_install_python_deps.py
pw_build/project_builder.py
pw_build/project_builder_argparse.py
pw_build/project_builder_context.py
pw_build/project_builder_prefs.py
pw_build/project_builder_presubmit_runner.py
pigweed-0.0.24.dist-info/METADATA
pigweed-0.0.24.dist-info/WHEEL
pigweed-0.0.24.dist-info/entry_points.txt
pigweed-0.0.24.dist-info/top_level.txt
pigweed-0.0.24.dist-info/RECORD
